Adafruit_TMP/TMP006.py
Adafruit_TMP/__init__.py
Adafruit_TMP-1.6.1.dist-info/metadata.json
Adafruit_TMP-1.6.1.dist-info/METADATA
Adafruit_TMP-1.6.1.dist-info/RECORD
Adafruit_TMP-1.6.1.dist-info/WHEEL
Adafruit_TMP-1.6.1.dist-info/DESCRIPTION.rst
Adafruit_TMP-1.6.1.dist-info/dependency_links.txt
Adafruit_TMP-1.6.1.dist-info/top_level.txt
