Metadata-Version: 2.0
Name: Adafruit-TMP
Version: 1.6.1
Summary: Library for accessing the TMP006 & TMP007  non-contact temperature sensor on a Raspberry Pi or Beaglebone Black.
Home-page: https://github.com/adafruit/Adafruit_Python_TMP/
Author: Tony DiCola
Author-email: tdicola@adafruit.com
License: MIT
Platform: UNKNOWN
Requires-Dist: Adafruit-GPIO (>=0.6.5)
